[{"country":"Palestine","name":"Al-Aqsa University","domain":"http://www.alaqsa.edu.ps/"},{"country":"Palestine","name":"Al-Azhar University of Gaza","domain":"http://www.alazhar.edu.ps/"},{"country":"Palestine","name":"Al-Quds Open University","domain":"http://www.qou.edu/"},{"country":"Palestine","name":"Al-Quds University - The Arab University in Jerusalem","domain":"https://www.alquds.edu/"},{"country":"Palestine","name":"An-Najah National University","domain":"https://www.najah.edu/"},{"country":"Palestine","name":"Arab American University - Jenin","domain":"https://www.aaup.edu/"},{"country":"Palestine","name":"Bethlehem University","domain":"https://www.bethlehem.edu"},{"country":"Palestine","name":"Birzeit University","domain":"http://www.birzeit.edu"},{"country":"Palestine","name":"Hebron University","domain":"https://www.hebron.edu"},{"country":"Palestine","name":"Islamic University of Gaza","domain":"http://www.iugaza.edu.ps/"},{"country":"Palestine","name":"Israa University Gaza","domain":"https://israa.edu.ps/"},{"country":"Palestine","name":"Palestine Polytechnic University","domain":"https://www.ppu.edu/"},{"country":"Palestine","name":"Palestine Technical College-Dier Elbalah","domain":"https://www.ptcdb.edu.ps/"},{"country":"Palestine","name":"Palestine Technical University - Kadoorie","domain":"http://www.ptuk.edu.ps/"},{"country":"Palestine","name":"Ummah University","domain":"http://www.uou.edu.ps/"},{"country":"Palestine","name":"University College of Applied Sciences","domain":"http://www.ucas.edu.ps/"},{"country":"Palestine","name":"University of Palestine","domain":"http://www.up.edu.ps/"}]