[{"country":"Tunisia","name":"Instituts Supérieurs de Formation des Maîtres","domain":"http://www.disfm.rnu.tn/"},{"country":"Tunisia","name":"Instituts Supérieurs des Etudes Technologiques","domain":"http://www.isetr.rnu.tn/"},{"country":"Tunisia","name":"Institut Supérieur de Gestion de Tunis","domain":"http://www.isg.rnu.tn/"},{"country":"Tunisia","name":"Université Centrale","domain":"http://www.ucaat.com/"},{"country":"Tunisia","name":"Université de Carthage","domain":"http://www.ucar.rnu.tn/"},{"country":"Tunisia","name":"Université de Gabès","domain":"http://www.univgb.rnu.tn/"},{"country":"Tunisia","name":"Université de Gafsa","domain":"http://www.ugaf.rnu.tn/"},{"country":"Tunisia","name":"Université de Jendouba","domain":"http://www.uj.rnu.tn/"},{"country":"Tunisia","name":"Université de Kairouan","domain":"http://www.univ-k.rnu.tn/"},{"country":"Tunisia","name":"Université de la Manouba","domain":"http://www.uma.rnu.tn/"},{"country":"Tunisia","name":"Université de Monastir","domain":"http://www.um.rnu.tn/"},{"country":"Tunisia","name":"Université de Sfax","domain":"http://www.uss.rnu.tn/"},{"country":"Tunisia","name":"Université de Tunis","domain":"http://www.utunis.rnu.tn/"},{"country":"Tunisia","name":"Université de Tunis El Manar","domain":"http://www.utm.rnu.tn/"},{"country":"Tunisia","name":"Université du Centre, Sousse","domain":"http://www.uc.rnu.tn/"},{"country":"Tunisia","name":"Université Ez-Zitouna","domain":"http://www.uz.rnu.tn/"},{"country":"Tunisia","name":"Université Libre de Tunis","domain":"http://www.ult-tunisie.com/"},{"country":"Tunisia","name":"Université Virtuelle de Tunis","domain":"http://www.uvt.rnu.tn/"},{"country":"Tunisia","name":"University of Aviation and Technology","domain":"http://www.unat.ens.tn/"}]